{"cameraMode":{"drawMode":0,"name":"Shaded","section":"Shading Mode"},"sceneLighting":true,"audioPlay":false,"sceneViewState":{"m_AlwaysRefresh":false,"showFog":true,"showSkybox":true,"showFlares":true,"showImageEffects":true,"showParticleSystems":true,"showVisualEffectGraphs":true,"m_FxEnabled":true},"in2DMode":false,"pivot":{"x":-0.6281996965408325,"y":0.6394322514533997,"z":-0.03634798526763916},"rotation":{"x":-0.12739919126033784,"y":0.849814236164093,"z":-0.2395993024110794,"w":-0.451861709356308},"size":3.3334922790527345,"orthographic":false}